controlflow/__init__.py
controlflow/_version.py
controlflow/decorators.py
controlflow/defaults.py
controlflow/instructions.py
controlflow/plan.py
controlflow/run.py
controlflow/settings.py
controlflow/stream.py
controlflow/agents/__init__.py
controlflow/agents/agent.py
controlflow/agents/names.py
controlflow/cli/dev.py
controlflow/cli/main.py
controlflow/events/__init__.py
controlflow/events/base.py
controlflow/events/events.py
controlflow/events/history.py
controlflow/events/message_compiler.py
controlflow/events/orchestrator_events.py
controlflow/events/task_events.py
controlflow/flows/__init__.py
controlflow/flows/flow.py
controlflow/flows/graph.py
controlflow/handlers/__init__.py
controlflow/handlers/callback_handler.py
controlflow/handlers/print_handler.py
controlflow/handlers/queue_handler.py
controlflow/llm/__init__.py
controlflow/llm/messages.py
controlflow/llm/models.py
controlflow/llm/rules.py
controlflow/memory/__init__.py
controlflow/memory/async_memory.py
controlflow/memory/memory.py
controlflow/memory/providers/__init__.py
controlflow/memory/providers/chroma.py
controlflow/memory/providers/lance.py
controlflow/memory/providers/postgres.py
controlflow/orchestration/__init__.py
controlflow/orchestration/conditions.py
controlflow/orchestration/handler.py
controlflow/orchestration/orchestrator.py
controlflow/orchestration/prompt_templates.py
controlflow/orchestration/turn_strategies.py
controlflow/orchestration/prompt_templates/agent.jinja
controlflow/orchestration/prompt_templates/flow.jinja
controlflow/orchestration/prompt_templates/instructions.jinja
controlflow/orchestration/prompt_templates/llm_instructions.jinja
controlflow/orchestration/prompt_templates/memories.jinja
controlflow/orchestration/prompt_templates/task.jinja
controlflow/orchestration/prompt_templates/tasks.jinja
controlflow/orchestration/prompt_templates/tools.jinja
controlflow/planning/__init__.py
controlflow/tasks/__init__.py
controlflow/tasks/task.py
controlflow/tasks/validators.py
controlflow-0.12.0.dist-info/LICENSE
controlflow-0.12.0.dist-info/METADATA
controlflow-0.12.0.dist-info/WHEEL
controlflow-0.12.0.dist-info/entry_points.txt
controlflow-0.12.0.dist-info/top_level.txt
controlflow-0.12.0.dist-info/RECORD
