Metadata-Version: 2.2
Name: controlflow
Version: 0.12.0
Summary: A framework for building agentic LLM workflows
Author-email: Jeremiah Lowin <153965+jlowin@users.noreply.github.com>
Project-URL: Code, https://github.com/PrefectHQ/ControlFlow
Keywords: ai,chatbot,llm,ai orchestration,llm orchestration,agentic workflows,flow engineering,prefect,workflow,orchestration,python,GPT,openai,assistant,agents,AI agents,natural language processing
Requires-Python: >=3.9
License-File: LICENSE
Requires-Dist: prefect>=3.0
Requires-Dist: jinja2>=3.1.4
Requires-Dist: langchain_core>=0.3
Requires-Dist: langchain_openai>=0.2
Requires-Dist: langchain-anthropic>=0.2
Requires-Dist: markdownify>=0.12.1
Requires-Dist: openai>=1.55.3
Requires-Dist: pydantic-settings>=2.2.1
Requires-Dist: textual>=0.61.1
Requires-Dist: tiktoken>=0.7.0
Requires-Dist: typer>=0.10
Requires-Dist: ipython>=8.18.1
Provides-Extra: tests
Requires-Dist: chromadb; extra == "tests"
Requires-Dist: duckduckgo-search; extra == "tests"
Requires-Dist: langchain_community; extra == "tests"
Requires-Dist: langchain_google_genai; extra == "tests"
Requires-Dist: langchain_groq; extra == "tests"
Requires-Dist: langchain-ollama; extra == "tests"
Requires-Dist: pytest-asyncio!=0.22.0,<0.23.0,>=0.18.2; extra == "tests"
Requires-Dist: pytest-env<2.0,>=0.8; extra == "tests"
Requires-Dist: pytest-rerunfailures<14,>=10; extra == "tests"
Requires-Dist: pytest-sugar<2.0,>=0.9; extra == "tests"
Requires-Dist: pytest>=7.0; extra == "tests"
Requires-Dist: pytest-timeout; extra == "tests"
Requires-Dist: pytest-xdist; extra == "tests"
Provides-Extra: dev
Requires-Dist: controlflow[tests]; extra == "dev"
Requires-Dist: ipython; extra == "dev"
Requires-Dist: pdbpp; extra == "dev"
Requires-Dist: pre-commit; extra == "dev"
Requires-Dist: ruff>=0.3.4; extra == "dev"
Requires-Dist: textual-dev; extra == "dev"
Requires-Dist: mypy; extra == "dev"
